techdraw/__init__.py
techdraw/demo.py
techdraw/gearwheel/__init__.py
techdraw/gearwheel/construction.py
techdraw/gearwheel/construction.svg
techdraw/gearwheel/svg.py
techdraw/gearwheel/demo/gearwheel-pair-1.svg
techdraw/gearwheel/demo/gearwheel-pair-2.svg
techdraw/gearwheel/demo/gearwheel-sample.svg
techdraw/involute/__init__.py
techdraw/involute/demo.py
techdraw/involute/demo.svg
techdraw/spirograph/__init__.py
techdraw/spirograph/compile.py
techdraw/spirograph/gen.py
techdraw/spirograph/samples/1.spiro
techdraw/spirograph/samples/1.svg
techdraw-0.0.5.dist-info/METADATA
techdraw-0.0.5.dist-info/WHEEL
techdraw-0.0.5.dist-info/licenses/LICENSE
techdraw-0.0.5.dist-info/RECORD
